cryptofinance/__init__.py
cryptofinance/__main__.py
cryptofinance-0.0.1.dist-info/METADATA
cryptofinance-0.0.1.dist-info/RECORD
cryptofinance-0.0.1.dist-info/WHEEL
cryptofinance-0.0.1.dist-info/top_level.txt
