Metadata-Version: 2.1
Name: cryptofinance
Version: 0.0.1
Summary: One API connecting you to cryptocurrency exchanges, indices, on-chain and social data.
Home-page: https://github.com/cryptofinance-ai/cryptofinance-api
Author: CRYPTOFINANCE
Author-email: support@cryptofinance.ai
License: MIT
Platform: UNKNOWN
Classifier: License :: OSI Approved :: MIT License
Classifier: Programming Language :: Python :: 3
Classifier: Topic :: Office/Business :: Financial
Classifier: Topic :: Internet :: WWW/HTTP
Classifier: Topic :: Software Development :: Libraries
Requires-Dist: requests
Requires-Dist: ujson
